{
  "version": "5",
  "dialect": "mysql",
  "id": "ca147c5b-c817-4963-862f-5df2a5896ab8",
  "prevId": "ac5433c4-2f27-456b-a12a-f8c377cf63eb",
  "tables": {
    "scaleit_user": {
      "name": "scaleit_user",
      "columns": {
        "id": {
          "name": "id",
          "type": "varchar(255)",
          "primaryKey": false,
          "notNull": true,
          "autoincrement": false,
          "default": "(UUID())"
        },
        "name": {
          "name": "name",
          "type": "varchar(255)",
          "primaryKey": false,
          "notNull": false,
          "autoincrement": false
        },
        "email": {
          "name": "email",
          "type": "varchar(255)",
          "primaryKey": false,
          "notNull": true,
          "autoincrement": false
        },
        "password": {
          "name": "password",
          "type": "varchar(255)",
          "primaryKey": false,
          "notNull": true,
          "autoincrement": false
        },
        "emailVerified": {
          "name": "emailVerified",
          "type": "timestamp(3)",
          "primaryKey": false,
          "notNull": false,
          "autoincrement": false,
          "default": "CURRENT_TIMESTAMP(3)"
        },
        "image": {
          "name": "image",
          "type": "varchar(255)",
          "primaryKey": false,
          "notNull": false,
          "autoincrement": false
        }
      },
      "indexes": {
        "email_idx": {
          "name": "email_idx",
          "columns": [
            "email"
          ],
          "isUnique": false
        },
        "id_idx": {
          "name": "id_idx",
          "columns": [
            "id"
          ],
          "isUnique": true
        }
      },
      "foreignKeys": {},
      "compositePrimaryKeys": {
        "scaleit_user_id": {
          "name": "scaleit_user_id",
          "columns": [
            "id"
          ]
        }
      },
      "uniqueConstraints": {}
    }
  },
  "schemas": {},
  "_meta": {
    "schemas": {},
    "tables": {},
    "columns": {}
  }
}